{
  "idCertificate": 100670,
  "idTechnicalReglaments": [
    30
  ],
  "idCertScheme": null,
  "idObjectCertType": 3,
  "idCertType": 1,
  "isTs": false,
  "idProductSingleLists": [],
  "awaitForApprove": false,
  "idStatus": 1,
  "expiredInspectionControl": false,
  "editApp": null,
  "assignRegNumber": false,
  "number": "ТС RU С-FR.МТ25.В.01918",
  "certRegDate": "2015-12-21",
  "certEndDate": "2019-12-20",
  "idBlank": 356678,
  "blankNumber": "0356678",
  "noSanction": null,
  "batchInspection": null,
  "inspectionControlPlanDate": null,
  "idSigner": null,
  "idEmployee": null,
  "firstName": null,
  "surname": null,
  "patronymic": null,
  "annexes": [],
  "applicant": {
    "idLegalSubject": 208165,
    "idEgrul": null,
    "idApplicantType": 1,
    "idLegalSubjectType": 1,
    "fullName": "Общество с ограниченной ответственностью «Пежо Ситроен Рус»",
    "shortName": null,
    "idPerson": 418793,
    "surname": null,
    "firstName": null,
    "patronymic": null,
    "headPosition": null,
    "ogrn": "1047796295744",
    "ogrnAssignDate": null,
    "inn": null,
    "kpp": null,
    "idLegalForm": null,
    "regDate": null,
    "regOrganName": null,
    "addlRegInfo": null,
    "isEecRegister": null,
    "contacts": [
      {
        "idContact": 251724,
        "idContactType": 1,
        "value": "+74959811410"
      },
      {
        "idContact": 251725,
        "idContactType": 3,
        "value": "+74959811411"
      },
      {
        "idContact": 251726,
        "idContactType": 4,
        "value": "pcr-homologation@mpsa.com"
      }
    ],
    "addresses": [
      {
        "idAddress": 639382,
        "idAddrType": 1,
        "idCodeOksm": "643",
        "oksmShort": null,
        "idSubject": "0c5b2444-70a0-4932-980c-b4dc0d3f02b5",
        "idDistrict": "0c5b2444-70a0-4932-980c-b4dc0d3f02b5",
        "idCity": null,
        "idLocality": null,
        "idStreet": null,
        "idHouse": null,
        "flat": null,
        "postCode": "101000",
        "fullAddress": "101000, РОССИЯ, город Москва, Чистопрудный бульвар, д. 17, стр. 1",
        "gln": null,
        "foreignDistrict": null,
        "foreignCity": null,
        "foreignLocality": null,
        "foreignStreet": null,
        "foreignHouse": null,
        "uniqueAddress": null,
        "otherGln": null,
        "glonass": null
      }
    ],
    "transnational": [],
    "passportIssueDate": null,
    "passportIssuedBy": null,
    "passportNum": null,
    "idPersonDoc": null
  },
  "applicantFilials": [],
  "manufIsApplicant": false,
  "manufacturer": {
    "idLegalSubject": 208166,
    "idEgrul": null,
    "idLegalSubjectType": 3,
    "fullName": "Automobiles Citroën. Сборочные заводы: Peugeot Citroën Automoviles España S.A.; Peugeot Citroën Automoveis Portugal SA",
    "shortName": null,
    "idPerson": 418794,
    "surname": null,
    "firstName": null,
    "patronymic": null,
    "headPosition": null,
    "ogrn": null,
    "ogrnAssignDate": null,
    "inn": null,
    "kpp": null,
    "idLegalForm": null,
    "regDate": null,
    "regOrganName": null,
    "addlRegInfo": null,
    "isEecRegister": null,
    "contacts": [],
    "addresses": [
      {
        "idAddress": 639383,
        "idAddrType": 1,
        "idCodeOksm": "250",
        "oksmShort": null,
        "idSubject": null,
        "idDistrict": null,
        "idCity": null,
        "idLocality": null,
        "idStreet": null,
        "idHouse": null,
        "flat": null,
        "postCode": null,
        "fullAddress": "ФРАНЦИЯ, Immeuble Colisée III, 6, rue Fructidor, 75835 Paris Cédex 17, Франция",
        "gln": null,
        "foreignDistrict": null,
        "foreignCity": null,
        "foreignLocality": null,
        "foreignStreet": null,
        "foreignHouse": null,
        "uniqueAddress": null,
        "otherGln": null,
        "glonass": null
      },
      {
        "idAddress": 639384,
        "idAddrType": 1,
        "idCodeOksm": "724",
        "oksmShort": null,
        "idSubject": null,
        "idDistrict": null,
        "idCity": null,
        "idLocality": null,
        "idStreet": null,
        "idHouse": null,
        "flat": null,
        "postCode": null,
        "fullAddress": "ИСПАНИЯ, Centro de Vigo, Avenida Citroën,  N 3 y 5 (zona franca), 36210 Vigo (Pontevedra), Испания",
        "gln": null,
        "foreignDistrict": null,
        "foreignCity": null,
        "foreignLocality": null,
        "foreignStreet": null,
        "foreignHouse": null,
        "uniqueAddress": null,
        "otherGln": null,
        "glonass": null
      },
      {
        "idAddress": 639385,
        "idAddrType": 1,
        "idCodeOksm": "620",
        "oksmShort": null,
        "idSubject": null,
        "idDistrict": null,
        "idCity": null,
        "idLocality": null,
        "idStreet": null,
        "idHouse": null,
        "flat": null,
        "postCode": null,
        "fullAddress": "ПОРТУГАЛИЯ, Centro de produçao de Mangualde, Apartado 27, 3531-952 Mangualde, Португалия",
        "gln": null,
        "foreignDistrict": null,
        "foreignCity": null,
        "foreignLocality": null,
        "foreignStreet": null,
        "foreignHouse": null,
        "uniqueAddress": null,
        "otherGln": null,
        "glonass": null
      }
    ],
    "transnational": [],
    "passportIssueDate": null,
    "passportIssuedBy": null,
    "passportNum": null,
    "idPersonDoc": null
  },
  "manufacturerFilials": [],
  "certificationAuthority": {
    "idCertificationAuthority": 104074,
    "fullName": "Орган по сертификации автомототехники - механических транспортных средств, запасных частей и принадлежностей АНО \"Центр содействия сертификации автомототехники\"",
    "accredOrgName": null,
    "attestatRegNumber": "RA.RU.11МТ25",
    "attestatRegDate": "2014-12-30",
    "attestatEndDate": null,
    "idRal": 1022,
    "ogrn": null,
    "idPerson": 418796,
    "firstName": "Александр",
    "surname": "Гусаров",
    "patronymic": "Павлович",
    "contacts": [
      {
        "idContact": 193506,
        "idContactType": 4,
        "value": "mt25@cssamt.ru"
      }
    ],
    "addresses": [
      {
        "idAddress": 639386,
        "idAddrType": 3,
        "idCodeOksm": "643",
        "oksmShort": null,
        "idSubject": "29251dcf-00a1-4e34-98d4-5c47484a36d4",
        "idDistrict": "29251dcf-00a1-4e34-98d4-5c47484a36d4",
        "idCity": null,
        "idLocality": null,
        "idStreet": null,
        "idHouse": null,
        "flat": null,
        "postCode": "141830",
        "fullAddress": "141830, Россия, Московская обл., Дмитровский район, п. Автополигон, НИЦИАМТ",
        "gln": null,
        "foreignDistrict": null,
        "foreignCity": null,
        "foreignLocality": null,
        "foreignStreet": null,
        "foreignHouse": null,
        "uniqueAddress": null,
        "otherGln": null,
        "glonass": null
      },
      {
        "idAddress": 639387,
        "idAddrType": 3,
        "idCodeOksm": "643",
        "oksmShort": null,
        "idSubject": "29251dcf-00a1-4e34-98d4-5c47484a36d4",
        "idDistrict": "29251dcf-00a1-4e34-98d4-5c47484a36d4",
        "idCity": null,
        "idLocality": null,
        "idStreet": null,
        "idHouse": null,
        "flat": null,
        "postCode": "141830",
        "fullAddress": "141830, Россия, Московская область, Дмитровский район, п. Новосиньково, дом 115-15",
        "gln": null,
        "foreignDistrict": null,
        "foreignCity": null,
        "foreignLocality": null,
        "foreignStreet": null,
        "foreignHouse": null,
        "uniqueAddress": null,
        "otherGln": null,
        "glonass": null
      },
      {
        "idAddress": 639388,
        "idAddrType": 1,
        "idCodeOksm": null,
        "oksmShort": null,
        "idSubject": "29251dcf-00a1-4e34-98d4-5c47484a36d4",
        "idDistrict": "29251dcf-00a1-4e34-98d4-5c47484a36d4",
        "idCity": null,
        "idLocality": null,
        "idStreet": null,
        "idHouse": null,
        "flat": null,
        "postCode": "141800",
        "fullAddress": "141800,Московская область, Дмитров-7, Центральный автополигон",
        "gln": null,
        "foreignDistrict": null,
        "foreignCity": null,
        "foreignLocality": null,
        "foreignStreet": null,
        "foreignHouse": null,
        "uniqueAddress": null,
        "otherGln": null,
        "glonass": null
      }
    ],
    "prevAttestatRegNumber": null,
    "prevIdRal": null
  },
  "product": {
    "idProduct": 104072,
    "idProductOrigin": "250",
    "fullName": "Транспортные средства марки CITROËN ",
    "marking": null,
    "usageScope": null,
    "storageCondition": null,
    "usageCondition": null,
    "batchSize": null,
    "batchId": null,
    "identification": "типа 7 коммерческого наименования BERLINGO,      модификации 7J5FS0, 7S5FS0 с двигателем 5FS (5F01), модификации 7J5FK0, 7J5FK0/1 с двигателем 5FK (5F01), модификации 7J9HP0, 7J9HP0/1, 7S9HP0, 7S9HP0/1, 7J9HP8/PS, 7J9HP8/1PS с дизельным двигателем 9HP (9H06), модификации 7J9HL0,7J9HL0/1, 7S9HL0, 7S9HL0/1 с дизельным двигателем 9HL (9H05) категории М1, модификации 7A5FK0, 7B5FK0, 7C5FK0, 7D5FK0 с двигателем 5FK (5F01), модификации 7A9HF0, 7A9HF0/1, 7B9HF0, 7B9HF0/1, 7C9HF0, 7C9HF0/1, 7D9HF0, 7D9HF0/1, 7E9HF0, 7E9HF0/1, 7F9HF0, 7F9HF0/1, 7L9HF0, 7L9HF0/1, 7R9HF0, 7R9HF0/1 с дизельным двигателем 9HP (9H06) категории N1, выпускаемые в соответствии с техническим регламентом Таможенного союза «О безопасности колесных транспортных средств» (ТР ТС 018/2011)",
    "identifications": [
      {
        "idIdentification": 186666,
        "annex": false,
        "name": null,
        "type": null,
        "tradeMark": null,
        "model": null,
        "article": null,
        "sort": null,
        "idOkpds": [],
        "idTnveds": [
          75407,
          75456
        ],
        "gtin": [],
        "lifeTime": null,
        "storageTime": null,
        "description": null,
        "amount": null,
        "idOkei": null,
        "factoryNumber": null,
        "productionDate": null,
        "expiryDate": null,
        "documents": [
          {
            "id": 117242,
            "name": null,
            "number": null,
            "date": null
          }
        ],
        "standards": [
          {
            "idStandard": 107644,
            "annex": false,
            "idDictStandard": null,
            "designation": null,
            "name": null,
            "section": null,
            "addlInfo": null,
            "idStatus": null
          }
        ]
      }
    ]
  },
  "experts": [
    {
      "idExpert": 106535,
      "idPerson": 418795,
      "idEmployee": null,
      "firstName": "Вячеслав",
      "surname": "Курков",
      "patronimyc": "Михайлович"
    }
  ],
  "statusChanges": [
    {
      "idChangeStatus": 122395,
      "idStatus": 6,
      "beginDate": "2015-12-27T11:05:56",
      "endDate": "2019-12-21T01:11:28.779",
      "comment": null,
      "idBasis": null,
      "docNumber": null,
      "publicated": true,
      "publishDate": "2018-04-06T14:56:18.819",
      "lkType": null,
      "idMrpa": null,
      "docName": null,
      "docDate": null,
      "idBasisSolutions": [],
      "levelStateControl": null,
      "typeStateControl": null,
      "idOngoingEvent": null,
      "idFileScan": null
    },
    {
      "idChangeStatus": 3746695,
      "idStatus": 1,
      "beginDate": "2019-12-21T01:11:28.779",
      "endDate": null,
      "comment": "Окончание срока действия сертификата",
      "idBasis": null,
      "docNumber": null,
      "publicated": true,
      "publishDate": "2019-12-21T01:11:28.932",
      "lkType": null,
      "idMrpa": null,
      "docName": null,
      "docDate": null,
      "idBasisSolutions": [],
      "levelStateControl": null,
      "typeStateControl": null,
      "idOngoingEvent": null,
      "idFileScan": null
    }
  ],
  "testingLabs": [
    {
      "idTestingLab": 113092,
      "annex": false,
      "idRal": null,
      "regNumber": null,
      "fullName": null,
      "beginDate": null,
      "endDate": null,
      "basis": null,
      "accredEec": false,
      "idAccredPlace": null,
      "importedForResearchTesting": null,
      "docConfirmCustom": [],
      "protocols": [],
      "actNumber": null,
      "actDate": null,
      "actIdentificationNumber": null,
      "actIdentificationDate": null
    }
  ],
  "productGroups": [],
  "documents": {
    "productTypeResearchConclusion": null,
    "productTypeCertificates": [],
    "productDesignResearchConclusion": null,
    "qmsCertificates": [],
    "manufacturingConditionAnalysisActs": [],
    "conformityAssessmentDocuments": [],
    "reportsOnTypeApprovalUnderUNRegulation": [],
    "protocolTestingTechnicalService": null,
    "commonDocuments": {},
    "samplingAct": null,
    "productCertificationContract": null,
    "applicationCertificationDecision": null,
    "foreignManufacturerContract": null,
    "rawMaterialCertificates": [],
    "vehicleChassisTypeApprovals": [],
    "applicantOtherDocuments": [],
    "expertConclusion": null
  },
  "idFgisRaV1": "a3a25f60-2884-4f5b-9603-4fcac815d81e",
  "changes": null,
  "awaitOperatorCheck": false,
  "productInfoOon106": null,
  "productMatchOON106": null,
  "idDeclarationChecker": null,
  "idMrpa": null,
  "showInOpenPart": true,
  "idCertBasis": null,
  "replacement": null,
  "replacedBy": null
}