{
  "idCertificate": 1006591,
  "idTechnicalReglaments": [
    97157
  ],
  "idCertScheme": null,
  "idObjectCertType": 1,
  "idCertType": 11,
  "isTs": false,
  "idProductSingleLists": [],
  "awaitForApprove": false,
  "idStatus": 1,
  "expiredInspectionControl": false,
  "editApp": null,
  "assignRegNumber": false,
  "number": "С-JP.АГ88.А.59305",
  "certRegDate": "2013-12-03",
  "certEndDate": null,
  "idBlank": 1782371,
  "blankNumber": "1782371",
  "noSanction": null,
  "batchInspection": null,
  "inspectionControlPlanDate": null,
  "idSigner": null,
  "idEmployee": null,
  "firstName": null,
  "surname": null,
  "patronymic": null,
  "annexes": [],
  "applicant": {
    "idLegalSubject": 2019926,
    "idEgrul": null,
    "idApplicantType": 3,
    "idLegalSubjectType": 4,
    "fullName": "-",
    "shortName": "-",
    "idPerson": null,
    "surname": null,
    "firstName": null,
    "patronymic": null,
    "headPosition": null,
    "ogrn": null,
    "ogrnAssignDate": null,
    "inn": null,
    "kpp": null,
    "idLegalForm": null,
    "regDate": null,
    "regOrganName": null,
    "addlRegInfo": null,
    "isEecRegister": null,
    "contacts": [],
    "addresses": [
      {
        "idAddress": 4773452,
        "idAddrType": 1,
        "idCodeOksm": null,
        "oksmShort": null,
        "idSubject": null,
        "idDistrict": null,
        "idCity": null,
        "idLocality": null,
        "idStreet": null,
        "idHouse": null,
        "flat": null,
        "postCode": null,
        "fullAddress": "Приморский край г.Владивосток ул.Русская д.67 к.1 кв.608",
        "gln": null,
        "foreignDistrict": null,
        "foreignCity": null,
        "foreignLocality": null,
        "foreignStreet": null,
        "foreignHouse": null,
        "uniqueAddress": null,
        "otherGln": null,
        "glonass": null
      }
    ],
    "transnational": [],
    "passportIssueDate": null,
    "passportIssuedBy": null,
    "passportNum": null,
    "idPersonDoc": null
  },
  "applicantFilials": [],
  "manufIsApplicant": false,
  "manufacturer": {
    "idLegalSubject": 2019927,
    "idEgrul": null,
    "idLegalSubjectType": 3,
    "fullName": "\"HONDA MOTOR CO., LTD.\"",
    "shortName": null,
    "idPerson": 4030644,
    "surname": null,
    "firstName": null,
    "patronymic": null,
    "headPosition": null,
    "ogrn": null,
    "ogrnAssignDate": null,
    "inn": null,
    "kpp": null,
    "idLegalForm": null,
    "regDate": null,
    "regOrganName": null,
    "addlRegInfo": null,
    "isEecRegister": null,
    "contacts": [],
    "addresses": [
      {
        "idAddress": 4773453,
        "idAddrType": 1,
        "idCodeOksm": null,
        "oksmShort": null,
        "idSubject": null,
        "idDistrict": null,
        "idCity": null,
        "idLocality": null,
        "idStreet": null,
        "idHouse": null,
        "flat": null,
        "postCode": null,
        "fullAddress": "2-1-1 Minami Aoyama, Minato-ku, Tokyo 107-8556, Japan.",
        "gln": null,
        "foreignDistrict": null,
        "foreignCity": null,
        "foreignLocality": null,
        "foreignStreet": null,
        "foreignHouse": null,
        "uniqueAddress": null,
        "otherGln": null,
        "glonass": null
      }
    ],
    "transnational": [],
    "passportIssueDate": null,
    "passportIssuedBy": null,
    "passportNum": null,
    "idPersonDoc": null
  },
  "manufacturerFilials": [
    {
      "idFilial": 173296,
      "fullName": null,
      "shortName": null,
      "idLegalForm": null,
      "kpp": null,
      "annex": false,
      "contacts": [],
      "addresses": [
        {
          "idAddress": 4773454,
          "idAddrType": 1,
          "idCodeOksm": null,
          "oksmShort": null,
          "idSubject": null,
          "idDistrict": null,
          "idCity": null,
          "idLocality": null,
          "idStreet": null,
          "idHouse": null,
          "flat": null,
          "postCode": null,
          "fullAddress": null,
          "gln": null,
          "foreignDistrict": null,
          "foreignCity": null,
          "foreignLocality": null,
          "foreignStreet": null,
          "foreignHouse": null,
          "uniqueAddress": null,
          "otherGln": null,
          "glonass": null
        }
      ]
    }
  ],
  "certificationAuthority": {
    "idCertificationAuthority": 1010001,
    "fullName": "Орган по сертификации продукции ООО \"Проксима\"",
    "accredOrgName": null,
    "attestatRegNumber": "РОСС RU.0001.11АГ88",
    "attestatRegDate": "2013-10-15",
    "attestatEndDate": null,
    "idRal": 17491,
    "ogrn": "1117746508450",
    "idPerson": 4030646,
    "firstName": "Л.",
    "surname": "Сумцов",
    "patronymic": "Л.",
    "contacts": [
      {
        "idContact": 645832,
        "idContactType": 1,
        "value": "+74956262462"
      }
    ],
    "addresses": [
      {
        "idAddress": 4773455,
        "idAddrType": 1,
        "idCodeOksm": null,
        "oksmShort": null,
        "idSubject": null,
        "idDistrict": null,
        "idCity": null,
        "idLocality": null,
        "idStreet": null,
        "idHouse": null,
        "flat": null,
        "postCode": "115682",
        "fullAddress": "115682,РФ, г. Москва, ул. Шипиловская, д. 64, корп. 1, оф. 147",
        "gln": null,
        "foreignDistrict": null,
        "foreignCity": null,
        "foreignLocality": null,
        "foreignStreet": null,
        "foreignHouse": null,
        "uniqueAddress": null,
        "otherGln": null,
        "glonass": null
      }
    ],
    "prevAttestatRegNumber": null,
    "prevIdRal": null
  },
  "product": {
    "idProduct": 1010006,
    "idProductOrigin": "392",
    "fullName": "Транспортное средство",
    "marking": null,
    "usageScope": null,
    "storageCondition": null,
    "usageCondition": null,
    "batchSize": null,
    "batchId": null,
    "identification": "HONDA CIVIC , категория M1, двигатель бензиновый, модель D15B, объем двигателя 1493 куб. см., 2000 г.в. Номер кузова: EU2-1000378. Экологический класс 4",
    "identifications": [
      {
        "idIdentification": 1530169,
        "annex": false,
        "name": null,
        "type": null,
        "tradeMark": null,
        "model": null,
        "article": null,
        "sort": null,
        "idOkpds": [],
        "idTnveds": [],
        "gtin": [],
        "lifeTime": null,
        "storageTime": null,
        "description": null,
        "amount": null,
        "idOkei": null,
        "factoryNumber": null,
        "productionDate": null,
        "expiryDate": null,
        "documents": [
          {
            "id": 1110498,
            "name": null,
            "number": null,
            "date": null
          }
        ],
        "standards": [
          {
            "idStandard": 1024270,
            "annex": false,
            "idDictStandard": null,
            "designation": null,
            "name": null,
            "section": null,
            "addlInfo": null,
            "idStatus": null
          }
        ]
      }
    ]
  },
  "experts": [
    {
      "idExpert": 1000113,
      "idPerson": 4030645,
      "idEmployee": null,
      "firstName": "Петр",
      "surname": "Малышкин",
      "patronimyc": "Валерьевич"
    }
  ],
  "statusChanges": [
    {
      "idChangeStatus": 6014328,
      "idStatus": 1,
      "beginDate": "2023-06-20T16:59:06.028518",
      "endDate": null,
      "comment": "Пункт 3.2 Решения Комиссии Таможенного союза от 09.12.2011 № 877",
      "idBasis": null,
      "docNumber": null,
      "publicated": true,
      "publishDate": null,
      "lkType": null,
      "idMrpa": null,
      "docName": null,
      "docDate": null,
      "idBasisSolutions": [],
      "levelStateControl": null,
      "typeStateControl": null,
      "idOngoingEvent": null,
      "idFileScan": null
    },
    {
      "idChangeStatus": 1500412,
      "idStatus": 6,
      "beginDate": "2013-12-03T00:00:00",
      "endDate": null,
      "comment": null,
      "idBasis": null,
      "docNumber": null,
      "publicated": true,
      "publishDate": "2018-04-20T18:34:43.775",
      "lkType": null,
      "idMrpa": null,
      "docName": null,
      "docDate": null,
      "idBasisSolutions": [],
      "levelStateControl": null,
      "typeStateControl": null,
      "idOngoingEvent": null,
      "idFileScan": null
    }
  ],
  "testingLabs": [
    {
      "idTestingLab": 1039543,
      "annex": false,
      "idRal": null,
      "regNumber": null,
      "fullName": null,
      "beginDate": null,
      "endDate": null,
      "basis": null,
      "accredEec": false,
      "idAccredPlace": null,
      "importedForResearchTesting": null,
      "docConfirmCustom": [],
      "protocols": [],
      "actNumber": null,
      "actDate": null,
      "actIdentificationNumber": null,
      "actIdentificationDate": null
    }
  ],
  "productGroups": [],
  "documents": {
    "productTypeResearchConclusion": null,
    "productTypeCertificates": [],
    "productDesignResearchConclusion": null,
    "qmsCertificates": [],
    "manufacturingConditionAnalysisActs": [],
    "conformityAssessmentDocuments": [],
    "reportsOnTypeApprovalUnderUNRegulation": [],
    "protocolTestingTechnicalService": null,
    "commonDocuments": {},
    "samplingAct": null,
    "productCertificationContract": null,
    "applicationCertificationDecision": null,
    "foreignManufacturerContract": null,
    "rawMaterialCertificates": [],
    "vehicleChassisTypeApprovals": [],
    "applicantOtherDocuments": [],
    "expertConclusion": null
  },
  "idFgisRaV1": "b532e204-a12b-4e4a-a6c6-102d2008da45",
  "changes": null,
  "awaitOperatorCheck": false,
  "productInfoOon106": null,
  "productMatchOON106": null,
  "idDeclarationChecker": null,
  "idMrpa": null,
  "showInOpenPart": true,
  "idCertBasis": null,
  "replacement": null,
  "replacedBy": null
}